fsc/__init__.py
fsc-0.0.2.dist-info/DESCRIPTION.rst
fsc-0.0.2.dist-info/METADATA
fsc-0.0.2.dist-info/RECORD
fsc-0.0.2.dist-info/WHEEL
fsc-0.0.2.dist-info/metadata.json
fsc-0.0.2.dist-info/top_level.txt
