Metadata-Version: 2.0
Name: fsc
Version: 0.0.2
Summary: Base package for frescolino's python modules.
Requires-Dist: setuptools
Requires-Dist: fsc.export
Requires-Dist: fsc.formatting
Requires-Dist: fsc.iohelper; python_version >= "3"
Requires-Dist: fsc.locker; python_version >= "3"
Requires-Dist: fsc.hdf5-io; python_version >= "3"
Requires-Dist: fsc.async-tools; python_version >= "3.5"
